hawkserver.py
hawk_server_asyncio-0.0.13.dist-info/LICENSE
hawk_server_asyncio-0.0.13.dist-info/METADATA
hawk_server_asyncio-0.0.13.dist-info/WHEEL
hawk_server_asyncio-0.0.13.dist-info/top_level.txt
hawk_server_asyncio-0.0.13.dist-info/RECORD
