Metadata-Version: 2.1
Name: hawk-server-asyncio
Version: 0.0.13
Summary: Utility function to perform the server-side of Hawk authentication for asyncio HTTP servers
Home-page: https://github.com/uktrade/hawk-server-asyncio
Author: Department for International Trade
Author-email: webops@digital.trade.gov.uk
License: UNKNOWN
Platform: UNKNOWN
Classifier: Programming Language :: Python :: 3
Classifier: License :: OSI Approved :: MIT License
Classifier: Framework :: AsyncIO
Requires-Python: >=3.6.3
